open_ortho_terminology-1.1.3.dist-info/licenses/LICENSE.md
terminology/__init__.py
terminology/constants.py
terminology/main.py
terminology/resources/__init__.py
terminology/resources/hl7.py
terminology/resources/naming_systems.py
terminology/resources/snomed.py
terminology/resources/code_systems/__init__.py
terminology/resources/code_systems/ada_1100_enumerated_terms.py
terminology/resources/code_systems/dentaleyepad_image_types.py
terminology/resources/code_systems/extraoral_2d_photographic_scheduled_protocol.py
terminology/resources/code_systems/extraoral_3d_visible_light_scheduled_protocol.py
terminology/resources/code_systems/intraoral_2d_photographic_scheduled_protocol.py
terminology/resources/code_systems/intraoral_3d_visible_light_scheduled_protocol.py
terminology/resources/value_sets/__init__.py
terminology/resources/value_sets/open_ortho_value_sets.py
terminology/resources/value_sets/scheduled_protocol.py
open_ortho_terminology-1.1.3.dist-info/METADATA
open_ortho_terminology-1.1.3.dist-info/WHEEL
open_ortho_terminology-1.1.3.dist-info/entry_points.txt
open_ortho_terminology-1.1.3.dist-info/top_level.txt
open_ortho_terminology-1.1.3.dist-info/RECORD
