Metadata-Version: 2.4
Name: open-ortho-terminology
Version: 1.1.3
Summary: A package for managing orthodontic codes and namespaces.
Author-email: Toni Magni <open-ortho@case.edu>
License: ## MIT License
Keywords: orthodontics,codes,fhir,healthcare,snomed
Classifier: Development Status :: 3 - Alpha
Classifier: Intended Audience :: Healthcare Industry
Classifier: Topic :: Software Development :: Libraries :: Python Modules
Classifier: License :: OSI Approved :: MIT License
Classifier: Programming Language :: Python :: 3
Classifier: Programming Language :: Python :: 3.6
Classifier: Programming Language :: Python :: 3.7
Classifier: Programming Language :: Python :: 3.8
Classifier: Programming Language :: Python :: 3.9
Classifier: Programming Language :: Python :: 3.10
Classifier: Programming Language :: Python :: 3.11
Classifier: Programming Language :: Python :: 3.12
Requires-Python: >=3.11
License-File: LICENSE.md
Requires-Dist: pydantic>=1.8.2
Requires-Dist: fhir.resources>=7.1.0
Dynamic: license-file
